nodenet.py
setup.py
nodenet.egg-info/PKG-INFO
nodenet.egg-info/SOURCES.txt
nodenet.egg-info/dependency_links.txt
nodenet.egg-info/top_level.txt